{
    "male": {
        "20": {
            "E1": {
                "M": "13.7510844177511",
                "SD": "3.78477683703487"
            },
            "E2": {
                "M": "12.2364614867137",
                "SD": "4.16567914799954"
            },
            "E3": {
                "M": "14.0741361959074",
                "SD": "3.67453671922156"
            },
            "E4": {
                "M": "11.6441532258065",
                "SD": "3.13270405740853"
            },
            "E5": {
                "M": "14.5996632996633",
                "SD": "3.41173650746889"
            },
            "E6": {
                "M": "14.3597972972973",
                "SD": "3.67236309741966"
            },
            "A1": {
                "M": "13.2302278820376",
                "SD": "3.71643356722785"
            },
            "A2": {
                "M": "14.9216605289588",
                "SD": "3.43320477562952"
            },
            "A3": {
                "M": "15.3897795591182",
                "SD": "3.08700688559274"
            },
            "A4": {
                "M": "12.815831344471",
                "SD": "4.06011972601918"
            },
            "A5": {
                "M": "12.0177673483071",
                "SD": "3.90738086122678"
            },
            "A6": {
                "M": "13.9912605042017",
                "SD": "3.34990252561265"
            },
            "C1": {
                "M": "15.3442016806722",
                "SD": "2.56728797470294"
            },
            "C2": {
                "M": "11.0898424404961",
                "SD": "3.96615130984576"
            },
            "C3": {
                "M": "15.3207674183777",
                "SD": "2.93448718412031"
            },
            "C4": {
                "M": "13.6686827956989",
                "SD": "3.66135031510724"
            },
            "C5": {
                "M": "12.3889075630252",
                "SD": "3.25620993545758"
            },
            "C6": {
                "M": "12.1692926583976",
                "SD": "4.06121449588576"
            },
            "N1": {
                "M": "11.6731154102735",
                "SD": "3.75410588711893"
            },
            "N2": {
                "M": "11.862323707186",
                "SD": "4.4275055901419"
            },
            "N3": {
                "M": "10.5293722725747",
                "SD": "4.23052087722015"
            },
            "N4": {
                "M": "12.3858823529412",
                "SD": "3.81882072740936"
            },
            "N5": {
                "M": "11.6257114161366",
                "SD": "3.26326164212383"
            },
            "N6": {
                "M": "9.56812080536914",
                "SD": "3.35247131825885"
            },
            "O1": {
                "M": "16.6352980576021",
                "SD": "2.9674865476181"
            },
            "O2": {
                "M": "14.4734899328859",
                "SD": "3.88604485916353"
            },
            "O3": {
                "M": "14.4408602150537",
                "SD": "3.36714683089255"
            },
            "O4": {
                "M": "12.7880617035547",
                "SD": "3.17868060648911"
            },
            "O5": {
                "M": "15.4562520952062",
                "SD": "3.51808782596198"
            },
            "O6": {
                "M": "11.861673414305",
                "SD": "3.18912714187681"
            },
            "E": {
                "M": "80.669348939283",
                "SD": "15.5320695757498"
            },
            "A": {
                "M": "82.3280581693754",
                "SD": "14.6944253310002"
            },
            "C": {
                "M": "80.1296903460837",
                "SD": "14.673807884847"
            },
            "N": {
                "M": "67.6470800288395",
                "SD": "15.8110631901334"
            },
            "O": {
                "M": "85.7014166363966",
                "SD": "12.5585628806059"
            }
        },
        "40": {
            "E1": {
                "M": "13.7510844177511",
                "SD": "3.78477683703487"
            },
            "E2": {
                "M": "12.2364614867137",
                "SD": "4.16567914799954"
            },
            "E3": {
                "M": "14.0741361959074",
                "SD": "3.67453671922156"
            },
            "E4": {
                "M": "11.6441532258065",
                "SD": "3.13270405740853"
            },
            "E5": {
                "M": "14.5996632996633",
                "SD": "3.41173650746889"
            },
            "E6": {
                "M": "14.3597972972973",
                "SD": "3.67236309741966"
            },
            "A1": {
                "M": "12.7640564826701",
                "SD": "3.73671823267135"
            },
            "A2": {
                "M": "15.9950751684811",
                "SD": "3.22177041737883"
            },
            "A3": {
                "M": "15.4186824498199",
                "SD": "2.98006260695134"
            },
            "A4": {
                "M": "14.6241134751773",
                "SD": "3.73748350507693"
            },
            "A5": {
                "M": "11.4008232570105",
                "SD": "3.61138181046417"
            },
            "A6": {
                "M": "13.8082580645161",
                "SD": "3.37520093445473"
            },
            "C1": {
                "M": "15.8408624229979",
                "SD": "2.40918944083114"
            },
            "C2": {
                "M": "12.0684400826446",
                "SD": "4.282966671321"
            },
            "C3": {
                "M": "15.6737899073121",
                "SD": "2.81206754480215"
            },
            "C4": {
                "M": "15.4479112944817",
                "SD": "3.41146839440233"
            },
            "C5": {
                "M": "13.2415221330572",
                "SD": "3.32946840775889"
            },
            "C6": {
                "M": "13.3893188854489",
                "SD": "4.04029758731059"
            },
            "N1": {
                "M": "11.6731154102735",
                "SD": "3.75410588711893"
            },
            "N2": {
                "M": "11.862323707186",
                "SD": "4.4275055901419"
            },
            "N3": {
                "M": "10.5293722725747",
                "SD": "4.23052087722015"
            },
            "N4": {
                "M": "12.3858823529412",
                "SD": "3.81882072740936"
            },
            "N5": {
                "M": "11.6257114161366",
                "SD": "3.26326164212383"
            },
            "N6": {
                "M": "9.56812080536914",
                "SD": "3.35247131825885"
            },
            "O1": {
                "M": "15.994863893169",
                "SD": "3.16016080376328"
            },
            "O2": {
                "M": "15.0340030911901",
                "SD": "3.61463398829729"
            },
            "O3": {
                "M": "14.6379622446341",
                "SD": "3.25296423149461"
            },
            "O4": {
                "M": "13.2234234234235",
                "SD": "3.44038790191914"
            },
            "O5": {
                "M": "16.2652903225806",
                "SD": "3.26363869307611"
            },
            "O6": {
                "M": "11.6207251221394",
                "SD": "3.73896075941997"
            },
            "E": {
                "M": "79.1995432486439",
                "SD": "15.5513327987903"
            },
            "A": {
                "M": "84.2094504021449",
                "SD": "13.5576900664976"
            },
            "C": {
                "M": "85.7584852734923",
                "SD": "14.2793700309002"
            },
            "N": {
                "M": "66.670677112479",
                "SD": "16.5915130682706"
            },
            "O": {
                "M": "86.8870607919687",
                "SD": "12.7509045772121"
            }
        },
        "60": {
            "E1": {
                "M": "13.3696450428397",
                "SD": "3.73417694376959"
            },
            "E2": {
                "M": "10.5165644171779",
                "SD": "3.72149714601841"
            },
            "E3": {
                "M": "14.9925925925926",
                "SD": "3.55218130647371"
            },
            "E4": {
                "M": "12.4034440344403",
                "SD": "3.26454123933663"
            },
            "E5": {
                "M": "11.8304239401496",
                "SD": "3.28560163397877"
            },
            "E6": {
                "M": "14.4292742927429",
                "SD": "3.27574743695694"
            },
            "A1": {
                "M": "13.4612546125461",
                "SD": "3.63243962590317"
            },
            "A2": {
                "M": "16.964590964591",
                "SD": "2.88151794119765"
            },
            "A3": {
                "M": "15.7970838396112",
                "SD": "2.93546006483352"
            },
            "A4": {
                "M": "15.6125356125356",
                "SD": "3.44895727106698"
            },
            "A5": {
                "M": "11.8844282238443",
                "SD": "3.32598024001365"
            },
            "A6": {
                "M": "14.4308445532436",
                "SD": "3.2985333039738"
            },
            "C1": {
                "M": "16.2017114914426",
                "SD": "2.2785567389516"
            },
            "C2": {
                "M": "13.1176470588235",
                "SD": "4.32551367669832"
            },
            "C3": {
                "M": "16.5847665847666",
                "SD": "2.47090103271458"
            },
            "C4": {
                "M": "16.5705521472392",
                "SD": "2.97691636119328"
            },
            "C5": {
                "M": "13.979012345679",
                "SD": "3.17994394961847"
            },
            "C6": {
                "M": "14.7291666666667",
                "SD": "3.74545054639639"
            },
            "N1": {
                "M": "10.6532356532357",
                "SD": "3.59086026114353"
            },
            "N2": {
                "M": "11.5857843137255",
                "SD": "4.15526794010156"
            },
            "N3": {
                "M": "9.6753086419753",
                "SD": "3.89440443135483"
            },
            "N4": {
                "M": "11.6751515151515",
                "SD": "3.66844002156518"
            },
            "N5": {
                "M": "11.282208588957",
                "SD": "3.60096424851605"
            },
            "N6": {
                "M": "8.60321384425215",
                "SD": "3.39656780099247"
            },
            "O1": {
                "M": "14.8778998778999",
                "SD": "3.33862883948795"
            },
            "O2": {
                "M": "14.8538083538084",
                "SD": "3.59403688068972"
            },
            "O3": {
                "M": "14.8393077873918",
                "SD": "3.1936489443354"
            },
            "O4": {
                "M": "12.9411042944785",
                "SD": "3.56118389304281"
            },
            "O5": {
                "M": "15.6913580246914",
                "SD": "3.27798204117496"
            },
            "O6": {
                "M": "10.987684729064",
                "SD": "3.8886912533315"
            },
            "E": {
                "M": "77.6152777777777",
                "SD": "14.4373584294581"
            },
            "A": {
                "M": "88.4506828528074",
                "SD": "12.5566889132086"
            },
            "C": {
                "M": "91.3061224489796",
                "SD": "13.1183110605121"
            },
            "N": {
                "M": "63.7347767253045",
                "SD": "15.5776756495471"
            },
            "O": {
                "M": "83.9238095238095",
                "SD": "13.1195370534836"
            }
        },
        "95": {
            "E1": {
                "M": "14.3269230769231",
                "SD": "3.97403905684624"
            },
            "E2": {
                "M": "11",
                "SD": "3.76828873628335"
            },
            "E3": {
                "M": "14.6470588235294",
                "SD": "3.85135575823249"
            },
            "E4": {
                "M": "13.2156862745098",
                "SD": "3.15159467882655"
            },
            "E5": {
                "M": "11.7659574468085",
                "SD": "3.12223976154693"
            },
            "E6": {
                "M": "14.3469387755102",
                "SD": "3.67168796563744"
            },
            "A1": {
                "M": "13.6862745098039",
                "SD": "3.63587786416668"
            },
            "A2": {
                "M": "16.843137254902",
                "SD": "3.59094722333597"
            },
            "A3": {
                "M": "15.1730769230769",
                "SD": "3.38810580341631"
            },
            "A4": {
                "M": "15",
                "SD": "4.40201973845845"
            },
            "A5": {
                "M": "11.5576923076923",
                "SD": "3.44374090675835"
            },
            "A6": {
                "M": "13.75",
                "SD": "3.46339400577175"
            },
            "C1": {
                "M": "15.75",
                "SD": "3.37740473516249"
            },
            "C2": {
                "M": "13.9803921568627",
                "SD": "4.70527447054231"
            },
            "C3": {
                "M": "16.1176470588235",
                "SD": "3.73441860976259"
            },
            "C4": {
                "M": "16.0576923076923",
                "SD": "3.57778253999165"
            },
            "C5": {
                "M": "13.921568627451",
                "SD": "3.24248754665243"
            },
            "C6": {
                "M": "14.5769230769231",
                "SD": "4.00659335931512"
            },
            "N1": {
                "M": "10.7058823529412",
                "SD": "4.3418618939209"
            },
            "N2": {
                "M": "12.04",
                "SD": "4.68588849850358"
            },
            "N3": {
                "M": "8.30769230769231",
                "SD": "4.3001981784631"
            },
            "N4": {
                "M": "11.62",
                "SD": "4.21314754606315"
            },
            "N5": {
                "M": "10.64",
                "SD": "3.61267609555971"
            },
            "N6": {
                "M": "9.49019607843137",
                "SD": "4.29125878511007"
            },
            "O1": {
                "M": "14.2692307692308",
                "SD": "3.24258057855876"
            },
            "O2": {
                "M": "14.2352941176471",
                "SD": "4.11139020426968"
            },
            "O3": {
                "M": "13.7254901960784",
                "SD": "3.05992438712167"
            },
            "O4": {
                "M": "12.3529411764706",
                "SD": "3.23000637406036"
            },
            "O5": {
                "M": "13.3617021276596",
                "SD": "4.56558740406159"
            },
            "O6": {
                "M": "10.68",
                "SD": "3.70570437271501"
            },
            "E": {
                "M": "79.9767441860465",
                "SD": "14.5348323365648"
            },
            "A": {
                "M": "85.8409090909091",
                "SD": "15.8377576252509"
            },
            "C": {
                "M": "90.8367346938775",
                "SD": "17.5182606380403"
            },
            "N": {
                "M": "62.9318181818182",
                "SD": "20.5159016344189"
            },
            "O": {
                "M": "78.6904761904762",
                "SD": "14.1257213849687"
            }
        }
    },
    "female": {
        "20": {
            "E1": {
                "M": "14.3948962731779",
                "SD": "3.64801844592153"
            },
            "E2": {
                "M": "12.9905956112852",
                "SD": "4.16663514899079"
            },
            "E3": {
                "M": "13.9743637034305",
                "SD": "3.69051383592274"
            },
            "E4": {
                "M": "12.7281089036056",
                "SD": "3.11402870660531"
            },
            "E5": {
                "M": "14.5436821776715",
                "SD": "3.48830895847436"
            },
            "E6": {
                "M": "15.2959183673469",
                "SD": "3.46182452224827"
            },
            "A1": {
                "M": "13.4801026957638",
                "SD": "3.76479938945799"
            },
            "A2": {
                "M": "16.1931021763187",
                "SD": "2.93534906324831"
            },
            "A3": {
                "M": "16.7098312545854",
                "SD": "2.70628317768476"
            },
            "A4": {
                "M": "13.8853171155517",
                "SD": "4.12085109391454"
            },
            "A5": {
                "M": "13.2239382239382",
                "SD": "3.78493275144018"
            },
            "A6": {
                "M": "15.7758779187351",
                "SD": "2.82301902354686"
            },
            "C1": {
                "M": "15.3778920308483",
                "SD": "2.49098643987087"
            },
            "C2": {
                "M": "11.1656826568266",
                "SD": "4.20763936243064"
            },
            "C3": {
                "M": "15.7230003685956",
                "SD": "2.74839440531901"
            },
            "C4": {
                "M": "14.786620106598",
                "SD": "3.31859915586515"
            },
            "C5": {
                "M": "12.8047970479705",
                "SD": "3.18685119429113"
            },
            "C6": {
                "M": "11.9133480825958",
                "SD": "4.04982962237654"
            },
            "N1": {
                "M": "13.3518552367026",
                "SD": "3.65664551597455"
            },
            "N2": {
                "M": "13.0932156646443",
                "SD": "4.18445914732718"
            },
            "N3": {
                "M": "11.0996867514281",
                "SD": "4.18972884178539"
            },
            "N4": {
                "M": "12.2082799047444",
                "SD": "3.83887144818093"
            },
            "N5": {
                "M": "12.4354630823053",
                "SD": "3.33338295940079"
            },
            "N6": {
                "M": "11.2864785095001",
                "SD": "3.49776151070174"
            },
            "O1": {
                "M": "16.8457310370099",
                "SD": "2.91521212035164"
            },
            "O2": {
                "M": "16.0091709464417",
                "SD": "3.43334307908659"
            },
            "O3": {
                "M": "16.0783410138249",
                "SD": "2.99488579165793"
            },
            "O4": {
                "M": "12.8746543778801",
                "SD": "3.26414453734033"
            },
            "O5": {
                "M": "15.1409309198375",
                "SD": "3.49170905015332"
            },
            "O6": {
                "M": "12.1888396156689",
                "SD": "3.03478892215429"
            },
            "E": {
                "M": "83.813408723748",
                "SD": "15.1778628147862"
            },
            "A": {
                "M": "89.5603751465419",
                "SD": "13.2814169945335"
            },
            "C": {
                "M": "81.7419030376184",
                "SD": "14.2945435805594"
            },
            "N": {
                "M": "73.6152929493545",
                "SD": "15.7237008387254"
            },
            "O": {
                "M": "89.1510950371711",
                "SD": "11.8886714881531"
            }
        },
        "40": {
            "E1": {
                "M": "14.0318818040435",
                "SD": "3.69178174945901"
            },
            "E2": {
                "M": "11.900250548074",
                "SD": "4.09054642112215"
            },
            "E3": {
                "M": "14.1976123154257",
                "SD": "3.63818026617782"
            },
            "E4": {
                "M": "12.8252396668239",
                "SD": "3.26690863062709"
            },
            "E5": {
                "M": "12.8697973928067",
                "SD": "3.53349090422686"
            },
            "E6": {
                "M": "14.9818181818182",
                "SD": "3.31130233181067"
            },
            "A1": {
                "M": "13.1160505381376",
                "SD": "3.74918937467559"
            },
            "A2": {
                "M": "17.3586152635721",
                "SD": "2.64948774348017"
            },
            "A3": {
                "M": "16.8475",
                "SD": "2.55977637130763"
            },
            "A4": {
                "M": "15.557824358511",
                "SD": "3.54978015232166"
            },
            "A5": {
                "M": "12.9372169295642",
                "SD": "3.607213632633"
            },
            "A6": {
                "M": "15.5515132507449",
                "SD": "2.90532673667736"
            },
            "C1": {
                "M": "16.0326817826427",
                "SD": "2.35808227232182"
            },
            "C2": {
                "M": "12.6313977148223",
                "SD": "4.53765539362122"
            },
            "C3": {
                "M": "16.3436911487759",
                "SD": "2.54469747268024"
            },
            "C4": {
                "M": "16.1694091835136",
                "SD": "3.03903209803507"
            },
            "C5": {
                "M": "13.5304101838755",
                "SD": "3.27059204737733"
            },
            "C6": {
                "M": "12.8478806907379",
                "SD": "4.18705352701383"
            },
            "N1": {
                "M": "13.1672365557973",
                "SD": "3.70596700329324"
            },
            "N2": {
                "M": "12.7667085032947",
                "SD": "4.14025440077327"
            },
            "N3": {
                "M": "10.8224460884622",
                "SD": "4.08281168528784"
            },
            "N4": {
                "M": "12.2428928459857",
                "SD": "3.80880547681398"
            },
            "N5": {
                "M": "12.7624041321021",
                "SD": "3.60362584123125"
            },
            "N6": {
                "M": "10.7506261740764",
                "SD": "3.67178885919913"
            },
            "O1": {
                "M": "15.6943879943723",
                "SD": "3.34580675576687"
            },
            "O2": {
                "M": "16.0259415533677",
                "SD": "3.30088731954032"
            },
            "O3": {
                "M": "16.4486156733928",
                "SD": "2.7053165292189"
            },
            "O4": {
                "M": "12.7989666510099",
                "SD": "3.45817190055874"
            },
            "O5": {
                "M": "15.2966567257887",
                "SD": "3.50517264747127"
            },
            "O6": {
                "M": "12.041339201509",
                "SD": "3.46854909939264"
            },
            "E": {
                "M": "80.8055411255412",
                "SD": "14.7318522897992"
            },
            "A": {
                "M": "91.8105553367467",
                "SD": "11.7018451483811"
            },
            "C": {
                "M": "87.5038799793068",
                "SD": "13.9413450156432"
            },
            "N": {
                "M": "72.4718526100309",
                "SD": "16.2024117444569"
            },
            "O": {
                "M": "88.3478856360212",
                "SD": "12.2535645945109"
            }
        },
        "60": {
            "E1": {
                "M": "14.191054313099",
                "SD": "3.75784556620916"
            },
            "E2": {
                "M": "10.7848426461143",
                "SD": "3.8762113362032"
            },
            "E3": {
                "M": "14.4414996767938",
                "SD": "3.57776803890364"
            },
            "E4": {
                "M": "13.0891346779441",
                "SD": "3.54535242183356"
            },
            "E5": {
                "M": "11.0673575129534",
                "SD": "3.45651580391171"
            },
            "E6": {
                "M": "14.9406392694064",
                "SD": "3.34539141452749"
            },
            "A1": {
                "M": "13.7732819524727",
                "SD": "3.59742914927819"
            },
            "A2": {
                "M": "18.1998706338939",
                "SD": "2.1821933050933"
            },
            "A3": {
                "M": "17.0667098445596",
                "SD": "2.47634680730549"
            },
            "A4": {
                "M": "16.9722222222222",
                "SD": "2.95968596832904"
            },
            "A5": {
                "M": "13.4823378291586",
                "SD": "3.31689260244942"
            },
            "A6": {
                "M": "15.8770122343851",
                "SD": "2.74043666764268"
            },
            "C1": {
                "M": "16.5012853470437",
                "SD": "2.18751167997704"
            },
            "C2": {
                "M": "13.5854287556415",
                "SD": "4.51066340088129"
            },
            "C3": {
                "M": "17.2367741935484",
                "SD": "2.37483360444155"
            },
            "C4": {
                "M": "17.1689408706952",
                "SD": "2.77833848590757"
            },
            "C5": {
                "M": "14.2676962676963",
                "SD": "3.2202512722906"
            },
            "C6": {
                "M": "14.4058441558441",
                "SD": "3.97419775866143"
            },
            "N1": {
                "M": "12.0377962844331",
                "SD": "3.74480580606525"
            },
            "N2": {
                "M": "11.2136422136422",
                "SD": "4.05651247832979"
            },
            "N3": {
                "M": "10.1515544041451",
                "SD": "4.03617282045401"
            },
            "N4": {
                "M": "12.0551635663887",
                "SD": "3.76468079965527"
            },
            "N5": {
                "M": "11.9794608472401",
                "SD": "3.79579447734801"
            },
            "N6": {
                "M": "10.1547848426461",
                "SD": "3.61424780286871"
            },
            "O1": {
                "M": "14.5569131832797",
                "SD": "3.49753665687769"
            },
            "O2": {
                "M": "16.0249679897567",
                "SD": "3.16329305708815"
            },
            "O3": {
                "M": "16.4748711340206",
                "SD": "2.54235811155572"
            },
            "O4": {
                "M": "12.6651554404145",
                "SD": "3.47119293666613"
            },
            "O5": {
                "M": "14.9555125725339",
                "SD": "3.68466135070212"
            },
            "O6": {
                "M": "11.8094315245478",
                "SD": "3.70579154163577"
            },
            "E": {
                "M": "78.5167883211679",
                "SD": "14.4312711818634"
            },
            "A": {
                "M": "95.6892430278884",
                "SD": "10.1662733516441"
            },
            "C": {
                "M": "93.2143895348837",
                "SD": "13.3898130908866"
            },
            "N": {
                "M": "67.6075230660042",
                "SD": "16.4355222681519"
            },
            "O": {
                "M": "86.4197264218864",
                "SD": "12.4618813454717"
            }
        },
        "95": {
            "E1": {
                "M": "14.7941176470588",
                "SD": "3.61607586470326"
            },
            "E2": {
                "M": "10.2574257425743",
                "SD": "3.7380568892047"
            },
            "E3": {
                "M": "14.31",
                "SD": "3.70283811434015"
            },
            "E4": {
                "M": "12.3571428571429",
                "SD": "3.57323959973487"
            },
            "E5": {
                "M": "9.99",
                "SD": "3.25202345711967"
            },
            "E6": {
                "M": "15.9285714285714",
                "SD": "3.11382020814622"
            },
            "A1": {
                "M": "14.1941747572816",
                "SD": "3.52597713456486"
            },
            "A2": {
                "M": "18.5894736842105",
                "SD": "2.11124011576793"
            },
            "A3": {
                "M": "17.1666666666667",
                "SD": "2.24306779552325"
            },
            "A4": {
                "M": "17.8510638297872",
                "SD": "2.67588774057938"
            },
            "A5": {
                "M": "13.6078431372549",
                "SD": "3.49301102130417"
            },
            "A6": {
                "M": "15.9509803921569",
                "SD": "3.01605424151001"
            },
            "C1": {
                "M": "16.43",
                "SD": "2.3017560270543"
            },
            "C2": {
                "M": "14.7669902912621",
                "SD": "4.55511753468632"
            },
            "C3": {
                "M": "18.3267326732673",
                "SD": "1.81718964828159"
            },
            "C4": {
                "M": "17.2254901960784",
                "SD": "2.67702680778619"
            },
            "C5": {
                "M": "14.5339805825243",
                "SD": "3.43515714165372"
            },
            "C6": {
                "M": "15.0909090909091",
                "SD": "3.89947905754379"
            },
            "N1": {
                "M": "11.78",
                "SD": "3.93271695221797"
            },
            "N2": {
                "M": "10.9896907216495",
                "SD": "3.95151565162245"
            },
            "N3": {
                "M": "9.1",
                "SD": "3.77257514601409"
            },
            "N4": {
                "M": "12.03",
                "SD": "3.87807877040874"
            },
            "N5": {
                "M": "10.0294117647059",
                "SD": "3.67882859733545"
            },
            "N6": {
                "M": "10.21",
                "SD": "3.65506428801122"
            },
            "O1": {
                "M": "13.4",
                "SD": "4.21876519825171"
            },
            "O2": {
                "M": "16.1386138613861",
                "SD": "3.28033444322464"
            },
            "O3": {
                "M": "15.7",
                "SD": "3.01343791719824"
            },
            "O4": {
                "M": "11.8181818181818",
                "SD": "3.60658025701332"
            },
            "O5": {
                "M": "13.7254901960784",
                "SD": "3.82839020209629"
            },
            "O6": {
                "M": "10.5454545454546",
                "SD": "3.8525706426471"
            },
            "E": {
                "M": "77.6785714285714",
                "SD": "13.3282567070963"
            },
            "A": {
                "M": "97.4939759036145",
                "SD": "10.4827075886746"
            },
            "C": {
                "M": "96.1208791208791",
                "SD": "13.5432108164408"
            },
            "N": {
                "M": "64.5679012345679",
                "SD": "16.062330366112"
            },
            "O": {
                "M": "81.5783132530121",
                "SD": "15.4486722785153"
            }
        }
    }
}